{
    "tables": {
        "User": {
            "tableName": "User",
            "schema": {
                "id": {
                    "primaryKey": true,
                    "autoIncrement": true,
                    "field": "id",
                    "seqType": "Sequelize.INTEGER"
                },
                "full_name": {
                    "allowNull": false,
                    "field": "full_name",
                    "seqType": "Sequelize.STRING"
                },
                "email": {
                    "allowNull": false,
                    "field": "email",
                    "seqType": "Sequelize.STRING"
                },
                "password": {
                    "allowNull": false,
                    "field": "password",
                    "seqType": "Sequelize.STRING"
                },
                "created_at": {
                    "allowNull": false,
                    "field": "created_at",
                    "seqType": "Sequelize.DATE"
                },
                "updated_at": {
                    "allowNull": false,
                    "field": "updated_at",
                    "seqType": "Sequelize.DATE"
                }
            },
            "indexes": []
        }
    },
    "revision": 1
}